README.md
setup.py
websockets_assistant.py
websockets_assistant.egg-info/PKG-INFO
websockets_assistant.egg-info/SOURCES.txt
websockets_assistant.egg-info/dependency_links.txt
websockets_assistant.egg-info/requires.txt
websockets_assistant.egg-info/top_level.txt